NiChart_common_utils/__init__.py
NiChart_common_utils/nifti_parser.py
nichart_common_utils-0.1.0.dist-info/licenses/LICENSE
nichart_common_utils-0.1.0.dist-info/METADATA
nichart_common_utils-0.1.0.dist-info/WHEEL
nichart_common_utils-0.1.0.dist-info/top_level.txt
nichart_common_utils-0.1.0.dist-info/RECORD
