Metadata-Version: 2.4
Name: NiChart_common_utils
Version: 0.1.0
Summary: Common utilities for NiChart applications.
License:                                  Apache License
Requires-Python: >=3.8
License-File: LICENSE
Dynamic: license-file
